MANIFEST.in
README
setup.py
ulo/__init__.py
ulo/circuit.py
ulo/polarization.py
ulo/scrap.py
ulo/simulator.py
ulo/state.py
ulo/toolbox.py
ulo.egg-info/PKG-INFO
ulo.egg-info/SOURCES.txt
ulo.egg-info/dependency_links.txt
ulo.egg-info/pbr.json
ulo.egg-info/top_level.txt