Metadata-Version: 1.0
Name: ulo
Version: 0.1.1
Summary: Linear optics simulator
Home-page: https://github.com/peteshadbolt/ulo
Author: Pete Shadbolt
Author-email: hello@peteshadbolt.co.uk
License: UNKNOWN
Keywords: quantum
Platform: UNKNOWN
